hiro_batch_client/VERSION
hiro_batch_client/__init__.py
hiro_batch_client/batchclient.py
hiro_batch_client/version.py
hiro_batch_client-1.0.5.dist-info/METADATA
hiro_batch_client-1.0.5.dist-info/WHEEL
hiro_batch_client-1.0.5.dist-info/top_level.txt
hiro_batch_client-1.0.5.dist-info/RECORD
