Metadata-Version: 2.1
Name: hiro-batch-client
Version: 1.0.5
Summary: Hiro Client for batch commands against the Graph REST API of HIRO 7
Home-page: https://github.com/arago/hiro-batch-client-python
Author: arago GmbH
Author-email: info@arago.co
Maintainer: Wolfgang Hübner
License: MIT
Project-URL: GitHub, https://github.com/arago/hiro-batch-client-python
Project-URL: Documentation, https://github.com/arago/hiro-batch-client-python/blob/master/src/README.md
Project-URL: Changelog, https://github.com/arago/hiro-batch-client-python/blob/master/CHANGELOG.md
Keywords: arago HIRO7 API REST batch
Platform: UNKNOWN
Classifier: Programming Language :: Python :: 3
Classifier: Programming Language :: Python :: 3.7
Classifier: License :: OSI Approved :: MIT License
Classifier: Operating System :: OS Independent
Classifier: Intended Audience :: Developers
Classifier: Topic :: Software Development :: Libraries
Requires-Python: >=3.7
Requires-Dist: wheel
Requires-Dist: requests
Requires-Dist: hiro-graph-client (>=5.0.0)
